transfer_movil/__init__.py
transfer_movil/api_credentials.py
transfer_movil/api_payload.py
transfer_movil/api_payment.py
transfermovil_api-0.0.1.dist-info/LICENSE
transfermovil_api-0.0.1.dist-info/METADATA
transfermovil_api-0.0.1.dist-info/WHEEL
transfermovil_api-0.0.1.dist-info/top_level.txt
transfermovil_api-0.0.1.dist-info/RECORD
